asgi_logger/__init__.py
asgi_logger/middleware.py
asgi_logger/py.typed
asgi_logger/utils.py
asgi_logger-0.1.0.dist-info/LICENSE
asgi_logger-0.1.0.dist-info/WHEEL
asgi_logger-0.1.0.dist-info/METADATA
asgi_logger-0.1.0.dist-info/RECORD
