Metadata-Version: 2.1
Name: asgi-logger
Version: 0.1.0
Summary: Middleware based uvicorn access logger! :tada:
Home-page: https://github.com/Kludex/asgi-logger
License: MIT
Author: Marcelo Trylesinski
Author-email: marcelotryle@gmail.com
Requires-Python: >=3.8,<4.0
Classifier: Intended Audience :: Developers
Classifier: License :: OSI Approved :: MIT License
Classifier: Operating System :: OS Independent
Classifier: Programming Language :: Python
Classifier: Programming Language :: Python :: 3
Classifier: Programming Language :: Python :: 3 :: Only
Classifier: Programming Language :: Python :: 3.10
Classifier: Programming Language :: Python :: 3.8
Classifier: Programming Language :: Python :: 3.9
Classifier: Topic :: Software Development :: Libraries :: Python Modules
Requires-Dist: asgiref (>=3.4.1,<4.0.0)
Project-URL: Repository, https://github.com/Kludex/asgi-logger
